secret_type/__about__.py
secret_type/__init__.py
secret_type/exceptions.py
secret_type/monad.py
secret_type/py.typed
secret_type/containers/__init__.py
secret_type/containers/bool.py
secret_type/containers/number.py
secret_type/containers/secret.py
secret_type/containers/sequence.py
secret_type/typing/__init__.py
secret_type/typing/number_types.py
secret_type/typing/types.py
secret_type-0.3.0.dist-info/METADATA
secret_type-0.3.0.dist-info/WHEEL
secret_type-0.3.0.dist-info/licenses/LICENSE.txt
secret_type-0.3.0.dist-info/RECORD
