Metadata-Version: 2.1
Name: secret-type
Version: 0.3.0
Summary: A Rune-style secret type for sensitive values in Python.
Project-URL: Documentation, https://python-secret-type.readthedocs.io
Project-URL: Issues, https://github.com/yasyf/secret-type/issues
Project-URL: Source, https://github.com/yasyf/secret-type
Author-email: Yasyf Mohamedali <yasyfm@gmail.com>
License-File: LICENSE.txt
Keywords: secrets,security,sensitive,sensitive-data,sensitive-information,sensitive-values,type-hints,types,typing
Classifier: Development Status :: 4 - Beta
Classifier: Programming Language :: Python
Classifier: Programming Language :: Python :: 3.7
Classifier: Programming Language :: Python :: 3.8
Classifier: Programming Language :: Python :: 3.9
Classifier: Programming Language :: Python :: 3.10
Classifier: Programming Language :: Python :: 3.11
Classifier: Programming Language :: Python :: Implementation :: CPython
Classifier: Programming Language :: Python :: Implementation :: PyPy
Requires-Python: >=3.7
Requires-Dist: cryptography
Requires-Dist: typing-extensions
